dmriprep/VERSION
dmriprep/__about__.py
dmriprep/__init__.py
dmriprep/_version.py
dmriprep/conftest.py
dmriprep/cli/__init__.py
dmriprep/cli/parser.py
dmriprep/cli/run.py
dmriprep/cli/version.py
dmriprep/cli/workflow.py
dmriprep/config/__init__.py
dmriprep/config/reports-spec.yml
dmriprep/config/testing.py
dmriprep/data/__init__.py
dmriprep/data/boilerplate.bib
dmriprep/data/flirtsch/b02b0.cnf
dmriprep/data/flirtsch/b02b0_1.cnf
dmriprep/data/flirtsch/b02b0_2.cnf
dmriprep/data/flirtsch/b02b0_4.cnf
dmriprep/data/flirtsch/b02b0_quick.cnf
dmriprep/data/tests/config.toml
dmriprep/data/tests/THP/CHANGES
dmriprep/data/tests/THP/README
dmriprep/data/tests/THP/dataset_description.json
dmriprep/data/tests/THP/sub-THP0005/anat/sub-THP0005_T1w.json
dmriprep/data/tests/THP/sub-THP0005/anat/sub-THP0005_T1w.nii.gz
dmriprep/data/tests/THP/sub-THP0005/dwi/sub-THP0005_dwi.bval
dmriprep/data/tests/THP/sub-THP0005/dwi/sub-THP0005_dwi.bvec
dmriprep/data/tests/THP/sub-THP0005/dwi/sub-THP0005_dwi.json
dmriprep/data/tests/THP/sub-THP0005/dwi/sub-THP0005_dwi.nii.gz
dmriprep/interfaces/__init__.py
dmriprep/interfaces/images.py
dmriprep/interfaces/reports.py
dmriprep/interfaces/vectors.py
dmriprep/utils/__init__.py
dmriprep/utils/bids.py
dmriprep/utils/images.py
dmriprep/utils/misc.py
dmriprep/utils/vectors.py
dmriprep/workflows/__init__.py
dmriprep/workflows/base.py
dmriprep/workflows/dwi/__init__.py
dmriprep/workflows/dwi/base.py
dmriprep/workflows/dwi/eddy.py
dmriprep/workflows/dwi/outputs.py
dmriprep/workflows/dwi/util.py
dmriprep-0.5.0.dist-info/LICENSE
dmriprep-0.5.0.dist-info/METADATA
dmriprep-0.5.0.dist-info/WHEEL
dmriprep-0.5.0.dist-info/entry_points.txt
dmriprep-0.5.0.dist-info/top_level.txt
dmriprep-0.5.0.dist-info/RECORD
