Metadata-Version: 2.1
Name: dmriprep
Version: 0.5.0
Summary: dMRIPrep is a robust and easy-to-use pipeline for preprocessing of diverse dMRI data.
Home-page: UNKNOWN
Author: The NiPreps developers
Author-email: nipreps@gmail.com
License: Apache License, Version 2.0
Project-URL: Home, https://github.com/nipreps/dmriprep
Project-URL: Documentation, https://www.nipreps.org/dmriprep
Platform: UNKNOWN
Classifier: Development Status :: 3 - Alpha
Classifier: Intended Audience :: Science/Research
Classifier: Topic :: Scientific/Engineering :: Image Recognition
Classifier: License :: OSI Approved :: BSD License
Classifier: Programming Language :: Python :: 3.7
Classifier: Programming Language :: Python :: 3.8
Classifier: Programming Language :: Python :: 3.9
Requires-Python: >=3.7
Requires-Dist: dipy (>=1.0.0)
Requires-Dist: indexed-gzip (>=0.8.8)
Requires-Dist: nibabel (~=3.0)
Requires-Dist: nipype (<2.0,>=1.5.1)
Requires-Dist: niworkflows (<1.5,>=1.4.0rc5)
Requires-Dist: numpy
Requires-Dist: pybids (>=0.11.1)
Requires-Dist: pyyaml
Requires-Dist: sdcflows (~=2.0.1)
Requires-Dist: smriprep (>=0.8.0rc2)
Requires-Dist: svgutils (!=0.3.2)
Requires-Dist: templateflow (~=0.6)
Requires-Dist: toml
Provides-Extra: all
Requires-Dist: datalad ; extra == 'all'
Requires-Dist: nbsphinx ; extra == 'all'
Requires-Dist: packaging ; extra == 'all'
Requires-Dist: pydot (>=1.2.3) ; extra == 'all'
Requires-Dist: pydotplus ; extra == 'all'
Requires-Dist: sphinx (<3.0,>=2.1.2) ; extra == 'all'
Requires-Dist: sphinx-argparse ; extra == 'all'
Requires-Dist: sphinx-rtd-theme ; extra == 'all'
Requires-Dist: sphinxcontrib-apidoc (~=0.3.0) ; extra == 'all'
Requires-Dist: sphinxcontrib-napoleon ; extra == 'all'
Requires-Dist: sphinxcontrib-versioning ; extra == 'all'
Requires-Dist: duecredit ; extra == 'all'
Requires-Dist: psutil (>=5.4) ; extra == 'all'
Requires-Dist: popylar (>=0.2) ; extra == 'all'
Requires-Dist: pytest (>=4.4) ; extra == 'all'
Requires-Dist: pytest-xdist (>=2.0) ; extra == 'all'
Requires-Dist: pytest-cov (>=2.10.1) ; extra == 'all'
Requires-Dist: pytest-env ; extra == 'all'
Requires-Dist: coverage ; extra == 'all'
Provides-Extra: datalad
Requires-Dist: datalad ; extra == 'datalad'
Provides-Extra: doc
Requires-Dist: nbsphinx ; extra == 'doc'
Requires-Dist: packaging ; extra == 'doc'
Requires-Dist: pydot (>=1.2.3) ; extra == 'doc'
Requires-Dist: pydotplus ; extra == 'doc'
Requires-Dist: sphinx (<3.0,>=2.1.2) ; extra == 'doc'
Requires-Dist: sphinx-argparse ; extra == 'doc'
Requires-Dist: sphinx-rtd-theme ; extra == 'doc'
Requires-Dist: sphinxcontrib-apidoc (~=0.3.0) ; extra == 'doc'
Requires-Dist: sphinxcontrib-napoleon ; extra == 'doc'
Requires-Dist: sphinxcontrib-versioning ; extra == 'doc'
Provides-Extra: docs
Requires-Dist: nbsphinx ; extra == 'docs'
Requires-Dist: packaging ; extra == 'docs'
Requires-Dist: pydot (>=1.2.3) ; extra == 'docs'
Requires-Dist: pydotplus ; extra == 'docs'
Requires-Dist: sphinx (<3.0,>=2.1.2) ; extra == 'docs'
Requires-Dist: sphinx-argparse ; extra == 'docs'
Requires-Dist: sphinx-rtd-theme ; extra == 'docs'
Requires-Dist: sphinxcontrib-apidoc (~=0.3.0) ; extra == 'docs'
Requires-Dist: sphinxcontrib-napoleon ; extra == 'docs'
Requires-Dist: sphinxcontrib-versioning ; extra == 'docs'
Provides-Extra: duecredit
Requires-Dist: duecredit ; extra == 'duecredit'
Provides-Extra: popylar
Requires-Dist: popylar (>=0.2) ; extra == 'popylar'
Provides-Extra: resmon
Requires-Dist: psutil (>=5.4) ; extra == 'resmon'
Provides-Extra: style
Requires-Dist: flake8 (>=3.7.0) ; extra == 'style'
Provides-Extra: test
Requires-Dist: pytest (>=4.4) ; extra == 'test'
Requires-Dist: pytest-xdist (>=2.0) ; extra == 'test'
Requires-Dist: pytest-cov (>=2.10.1) ; extra == 'test'
Requires-Dist: pytest-env ; extra == 'test'
Requires-Dist: coverage ; extra == 'test'
Provides-Extra: tests
Requires-Dist: pytest (>=4.4) ; extra == 'tests'
Requires-Dist: pytest-xdist (>=2.0) ; extra == 'tests'
Requires-Dist: pytest-cov (>=2.10.1) ; extra == 'tests'
Requires-Dist: pytest-env ; extra == 'tests'
Requires-Dist: coverage ; extra == 'tests'
